{
  "checks": [
    {
      "ageHours": 0.01,
      "ageMs": 33444,
      "contentHash": "849c90e1738f4e52",
      "errors": [],
      "fetchedAt": 1781593490928,
      "name": "insight",
      "path": "public/newsdata/insight_latest.json",
      "status": "PASS",
      "storyCount": 605,
      "warnings": []
    },
    {
      "ageHours": 0.0,
      "ageMs": 10772,
      "contentHash": "9c99534f02ef",
      "errors": [],
      "fetchedAt": 1781593513600,
      "name": "sections",
      "path": "public/newsdata/sections_latest.json",
      "status": "PASS",
      "storyCount": 278,
      "warnings": []
    }
  ],
  "errors": [],
  "generatedAt": 1781593524372,
  "schemaVersion": 1,
  "status": "PASS",
  "thresholds": {
    "maxAgeHours": 6.0,
    "maxFutureSkewMinutes": 10.0
  },
  "warnings": []
}