{
  "checks": [
    {
      "ageHours": 0.01,
      "ageMs": 33641,
      "contentHash": "5d4aad70d381407b",
      "errors": [],
      "fetchedAt": 1781713533327,
      "name": "insight",
      "path": "public/newsdata/insight_latest.json",
      "status": "PASS",
      "storyCount": 772,
      "warnings": []
    },
    {
      "ageHours": 0.0,
      "ageMs": 12934,
      "contentHash": "e7886722677c",
      "errors": [],
      "fetchedAt": 1781713554034,
      "name": "sections",
      "path": "public/newsdata/sections_latest.json",
      "status": "PASS",
      "storyCount": 284,
      "warnings": []
    }
  ],
  "errors": [],
  "generatedAt": 1781713566968,
  "schemaVersion": 1,
  "status": "PASS",
  "thresholds": {
    "maxAgeHours": 6.0,
    "maxFutureSkewMinutes": 10.0
  },
  "warnings": []
}