{
  "checks": [
    {
      "ageHours": 0.01,
      "ageMs": 24325,
      "contentHash": "a0af227c529472ba",
      "errors": [],
      "fetchedAt": 1782572596169,
      "name": "insight",
      "path": "public/newsdata/insight_latest.json",
      "status": "PASS",
      "storyCount": 592,
      "warnings": []
    },
    {
      "ageHours": 0.0,
      "ageMs": 14400,
      "contentHash": "5fe4748ad473",
      "errors": [],
      "fetchedAt": 1782572606094,
      "name": "sections",
      "path": "public/newsdata/sections_latest.json",
      "status": "PASS",
      "storyCount": 286,
      "warnings": []
    }
  ],
  "errors": [],
  "generatedAt": 1782572620494,
  "schemaVersion": 1,
  "status": "PASS",
  "thresholds": {
    "maxAgeHours": 6.0,
    "maxFutureSkewMinutes": 10.0
  },
  "warnings": []
}