{
  "categoryCounts": {
    "alerts": 32,
    "shopping": 30
  },
  "contentClassCounts": {
    "upahead_alert": 32,
    "upahead_offer": 30
  },
  "contentHash": "8267a17a1a94",
  "contractVersion": "upahead-lifecycle-v1",
  "errors": [],
  "fetchedAt": 1781931023327,
  "generatedAt": 1781931036709,
  "horizon": {
    "alertFallbackHours": 24,
    "eventPastGraceHours": 24,
    "lookaheadDays": 7,
    "offerFallbackHours": 48,
    "plannerPastGraceHours": 6
  },
  "itemCount": 62,
  "lifecycleSummary": {
    "categoryCounts": {
      "alerts": 32,
      "shopping": 30
    },
    "contentClassCounts": {
      "upahead_alert": 32,
      "upahead_offer": 30
    },
    "horizonViolationCount": 0,
    "horizonViolationSample": [],
    "itemCount": 62,
    "plannerEligibleByLifecycleCount": 61,
    "visibleItemCount": 62
  },
  "plannerEligibleByLifecycleCount": 61,
  "schemaVersion": 1,
  "status": "PASS",
  "thresholds": {
    "eventPastGraceHours": 24,
    "lookaheadDays": 7,
    "minVisibleItems": 3,
    "plannerPastGraceHours": 6
  },
  "visibleItemCount": 62,
  "warnings": []
}